easybpy/__init__.py
easybpy/easybpy.py
easybpy-0.0.1.dist-info/METADATA
easybpy-0.0.1.dist-info/WHEEL
easybpy-0.0.1.dist-info/RECORD
