Metadata-Version: 2.1
Name: easybpy
Version: 0.0.1
Summary: 
License: MIT
Author: Danny Rakita
Author-email: daniel.rakita@yale.edu
Requires-Python: >=3.11,<3.12
Classifier: License :: OSI Approved :: MIT License
Classifier: Programming Language :: Python :: 3
Classifier: Programming Language :: Python :: 3.11
Requires-Dist: bpy (>=4.2.0,<5.0.0)
